sub_customizer/__init__.py
sub_customizer/__main__.py
sub_customizer/customizer.py
sub_customizer/datastructures.py
sub_customizer/api/__init__.py
sub_customizer/api/app.py
sub_customizer/api/config.py
sub_customizer/api/render.py
sub_customizer/api/endpoints/__init__.py
sub_customizer/api/endpoints/customizer.py
sub_customizer/api/templates/customizer.html
sub_customizer-0.1.2.dist-info/LICENSE
sub_customizer-0.1.2.dist-info/METADATA
sub_customizer-0.1.2.dist-info/WHEEL
sub_customizer-0.1.2.dist-info/entry_points.txt
sub_customizer-0.1.2.dist-info/top_level.txt
sub_customizer-0.1.2.dist-info/RECORD
