Metadata-Version: 2.1
Name: sub-customizer
Version: 0.1.2
Summary: Clash subscription customizer
Author: linux-fly
License: GPL-3.0
Project-URL: Homepage, https://github.com/linux-fly/sub-customizer
Project-URL: Repository, https://github.com/linux-fly/sub-customizer
Classifier: Programming Language :: Python :: 3 :: Only
Requires-Python: >=3.9
License-File: LICENSE
Requires-Dist: requests
Requires-Dist: pydantic
Requires-Dist: pydantic-settings
Requires-Dist: pyyaml
Provides-Extra: api
Requires-Dist: fastapi; extra == "api"
Requires-Dist: jinja2; extra == "api"
Requires-Dist: uvicorn[standard]; extra == "api"
